checkpadis/__init__.py
checkpadis/cli.py
checkpadis/github_utils.py
checkpadis-0.3.dist-info/METADATA
checkpadis-0.3.dist-info/WHEEL
checkpadis-0.3.dist-info/entry_points.txt
checkpadis-0.3.dist-info/top_level.txt
checkpadis-0.3.dist-info/RECORD
