Metadata-Version: 2.1
Name: checkpadis
Version: 0.3
Summary: Viabilidad 01
Author: PADIS
Classifier: Programming Language :: Python :: 3
Classifier: License :: OSI Approved :: MIT License
Classifier: Operating System :: OS Independent
Requires-Dist: click
Requires-Dist: colorama
Requires-Dist: requests
